{
      "audio_features": [
            {
                  "danceability": 0.549,
                  "energy": 0.259,
                  "key": 9,
                  "loudness": -17.532,
                  "mode": 1,
                  "speechiness": 0.0524,
                  "acousticness": 0.676,
                  "instrumentalness": 0,
                  "liveness": 0.0797,
                  "valence": 0.541,
                  "tempo": 95.093,
                  "type": "audio_features",
                  "id": "0BoCuzEjDEcULyknBHf3Ii",
                  "uri": "spotify:track:0BoCuzEjDEcULyknBHf3Ii",
                  "track_href": "https://api.spotify.com/v1/tracks/0BoCuzEjDEcULyknBHf3Ii",
                  "analysis_url": "https://api.spotify.com/v1/audio-analysis/0BoCuzEjDEcULyknBHf3Ii",
                  "duration_ms": 280107,
                  "time_signature": 4
            },
            {
                  "danceability": 0.541,
                  "energy": 0.334,
                  "key": 7,
                  "loudness": -18.603,
                  "mode": 1,
                  "speechiness": 0.0564,
                  "acousticness": 0.418,
                  "instrumentalness": 0,
                  "liveness": 0.067,
                  "valence": 0.606,
                  "tempo": 101.622,
                  "type": "audio_features",
                  "id": "6lCcA1ugWuQPBCHXecSwc8",
                  "uri": "spotify:track:6lCcA1ugWuQPBCHXecSwc8",
                  "track_href": "https://api.spotify.com/v1/tracks/6lCcA1ugWuQPBCHXecSwc8",
                  "analysis_url": "https://api.spotify.com/v1/audio-analysis/6lCcA1ugWuQPBCHXecSwc8",
                  "duration_ms": 294360,
                  "time_signature": 4
            },
            {
                  "danceability": 0.533,
                  "energy": 0.327,
                  "key": 4,
                  "loudness": -11.839,
                  "mode": 1,
                  "speechiness": 0.0306,
                  "acousticness": 0.738,
                  "instrumentalness": 0,
                  "liveness": 0.275,
                  "valence": 0.423,
                  "tempo": 94.996,
                  "type": "audio_features",
                  "id": "0dKnQQ0NNs4i7DvevY0DKv",
                  "uri": "spotify:track:0dKnQQ0NNs4i7DvevY0DKv",
                  "track_href": "https://api.spotify.com/v1/tracks/0dKnQQ0NNs4i7DvevY0DKv",
                  "analysis_url": "https://api.spotify.com/v1/audio-analysis/0dKnQQ0NNs4i7DvevY0DKv",
                  "duration_ms": 325400,
                  "time_signature": 4
            },
            {
                  "danceability": 0.331,
                  "energy": 0.668,
                  "key": 6,
                  "loudness": -8.768,
                  "mode": 0,
                  "speechiness": 0.0656,
                  "acousticness": 0.0108,
                  "instrumentalness": 3.13e-06,
                  "liveness": 0.177,
                  "valence": 0.478,
                  "tempo": 93.357,
                  "type": "audio_features",
                  "id": "4cZGdje7UXxBsJViy2Cs8Z",
                  "uri": "spotify:track:4cZGdje7UXxBsJViy2Cs8Z",
                  "track_href": "https://api.spotify.com/v1/tracks/4cZGdje7UXxBsJViy2Cs8Z",
                  "analysis_url": "https://api.spotify.com/v1/audio-analysis/4cZGdje7UXxBsJViy2Cs8Z",
                  "duration_ms": 284040,
                  "time_signature": 4
            },
            {
                  "danceability": 0.567,
                  "energy": 0.333,
                  "key": 4,
                  "loudness": -17.687,
                  "mode": 1,
                  "speechiness": 0.0425,
                  "acousticness": 0.54,
                  "instrumentalness": 0,
                  "liveness": 0.0736,
                  "valence": 0.53,
                  "tempo": 107.895,
                  "type": "audio_features",
                  "id": "7oo3L1ZPEQSavDVSnlOvDa",
                  "uri": "spotify:track:7oo3L1ZPEQSavDVSnlOvDa",
                  "track_href": "https://api.spotify.com/v1/tracks/7oo3L1ZPEQSavDVSnlOvDa",
                  "analysis_url": "https://api.spotify.com/v1/audio-analysis/7oo3L1ZPEQSavDVSnlOvDa",
                  "duration_ms": 258027,
                  "time_signature": 4
            },
            {
                  "danceability": 0.455,
                  "energy": 0.407,
                  "key": 4,
                  "loudness": -19.041,
                  "mode": 1,
                  "speechiness": 0.0988,
                  "acousticness": 0.291,
                  "instrumentalness": 0.000235,
                  "liveness": 0.067,
                  "valence": 0.442,
                  "tempo": 167.385,
                  "type": "audio_features",
                  "id": "1UsAjRCSavihMYsspqJz4e",
                  "uri": "spotify:track:1UsAjRCSavihMYsspqJz4e",
                  "track_href": "https://api.spotify.com/v1/tracks/1UsAjRCSavihMYsspqJz4e",
                  "analysis_url": "https://api.spotify.com/v1/audio-analysis/1UsAjRCSavihMYsspqJz4e",
                  "duration_ms": 196560,
                  "time_signature": 1
            },
            {
                  "danceability": 0.667,
                  "energy": 0.44,
                  "key": 7,
                  "loudness": -9.32,
                  "mode": 1,
                  "speechiness": 0.0333,
                  "acousticness": 0.837,
                  "instrumentalness": 0.0014,
                  "liveness": 0.198,
                  "valence": 0.34,
                  "tempo": 143.843,
                  "type": "audio_features",
                  "id": "4XYdH6H7haUCeEm9YezQ9K",
                  "uri": "spotify:track:4XYdH6H7haUCeEm9YezQ9K",
                  "track_href": "https://api.spotify.com/v1/tracks/4XYdH6H7haUCeEm9YezQ9K",
                  "analysis_url": "https://api.spotify.com/v1/audio-analysis/4XYdH6H7haUCeEm9YezQ9K",
                  "duration_ms": 271227,
                  "time_signature": 3
            },
            {
                  "danceability": 0.508,
                  "energy": 0.533,
                  "key": 4,
                  "loudness": -10.165,
                  "mode": 1,
                  "speechiness": 0.0412,
                  "acousticness": 0.587,
                  "instrumentalness": 0,
                  "liveness": 0.29,
                  "valence": 0.751,
                  "tempo": 151.441,
                  "type": "audio_features",
                  "id": "0ZEfn5WJYW9T7c9NdpBiNA",
                  "uri": "spotify:track:0ZEfn5WJYW9T7c9NdpBiNA",
                  "track_href": "https://api.spotify.com/v1/tracks/0ZEfn5WJYW9T7c9NdpBiNA",
                  "analysis_url": "https://api.spotify.com/v1/audio-analysis/0ZEfn5WJYW9T7c9NdpBiNA",
                  "duration_ms": 133013,
                  "time_signature": 4
            },
            {
                  "danceability": 0.598,
                  "energy": 0.562,
                  "key": 2,
                  "loudness": -10.205,
                  "mode": 1,
                  "speechiness": 0.049,
                  "acousticness": 0.225,
                  "instrumentalness": 0,
                  "liveness": 0.0864,
                  "valence": 0.567,
                  "tempo": 154.107,
                  "type": "audio_features",
                  "id": "5jyc2gfTkBHbIyMETSfq2u",
                  "uri": "spotify:track:5jyc2gfTkBHbIyMETSfq2u",
                  "track_href": "https://api.spotify.com/v1/tracks/5jyc2gfTkBHbIyMETSfq2u",
                  "analysis_url": "https://api.spotify.com/v1/audio-analysis/5jyc2gfTkBHbIyMETSfq2u",
                  "duration_ms": 205453,
                  "time_signature": 4
            },
            {
                  "danceability": 0.64,
                  "energy": 0.814,
                  "key": 11,
                  "loudness": -6.701,
                  "mode": 0,
                  "speechiness": 0.137,
                  "acousticness": 0.118,
                  "instrumentalness": 0,
                  "liveness": 0.223,
                  "valence": 0.782,
                  "tempo": 134.221,
                  "type": "audio_features",
                  "id": "5iehR5VxXMZpQ5MAmlY68f",
                  "uri": "spotify:track:5iehR5VxXMZpQ5MAmlY68f",
                  "track_href": "https://api.spotify.com/v1/tracks/5iehR5VxXMZpQ5MAmlY68f",
                  "analysis_url": "https://api.spotify.com/v1/audio-analysis/5iehR5VxXMZpQ5MAmlY68f",
                  "duration_ms": 233960,
                  "time_signature": 4
            },
            {
                  "danceability": 0.644,
                  "energy": 0.404,
                  "key": 0,
                  "loudness": -12.54,
                  "mode": 1,
                  "speechiness": 0.0348,
                  "acousticness": 0.159,
                  "instrumentalness": 0.000291,
                  "liveness": 0.167,
                  "valence": 0.689,
                  "tempo": 105.062,
                  "type": "audio_features",
                  "id": "7CdDIvw3jvjNaIs5m3mM4A",
                  "uri": "spotify:track:7CdDIvw3jvjNaIs5m3mM4A",
                  "track_href": "https://api.spotify.com/v1/tracks/7CdDIvw3jvjNaIs5m3mM4A",
                  "analysis_url": "https://api.spotify.com/v1/audio-analysis/7CdDIvw3jvjNaIs5m3mM4A",
                  "duration_ms": 268760,
                  "time_signature": 4
            },
            {
                  "danceability": 0.539,
                  "energy": 0.745,
                  "key": 9,
                  "loudness": -7.854,
                  "mode": 0,
                  "speechiness": 0.0279,
                  "acousticness": 0.451,
                  "instrumentalness": 0.000239,
                  "liveness": 0.103,
                  "valence": 0.78,
                  "tempo": 99.92,
                  "type": "audio_features",
                  "id": "661Ns9G25zHdih4qVshBO7",
                  "uri": "spotify:track:661Ns9G25zHdih4qVshBO7",
                  "track_href": "https://api.spotify.com/v1/tracks/661Ns9G25zHdih4qVshBO7",
                  "analysis_url": "https://api.spotify.com/v1/audio-analysis/661Ns9G25zHdih4qVshBO7",
                  "duration_ms": 288160,
                  "time_signature": 4
            },
            {
                  "danceability": 0.559,
                  "energy": 0.868,
                  "key": 5,
                  "loudness": -5.276,
                  "mode": 1,
                  "speechiness": 0.17,
                  "acousticness": 0.0475,
                  "instrumentalness": 0.000176,
                  "liveness": 0.776,
                  "valence": 0.609,
                  "tempo": 156.295,
                  "type": "audio_features",
                  "id": "5T8EDUDqKcs6OSOwEsfqG7",
                  "uri": "spotify:track:5T8EDUDqKcs6OSOwEsfqG7",
                  "track_href": "https://api.spotify.com/v1/tracks/5T8EDUDqKcs6OSOwEsfqG7",
                  "analysis_url": "https://api.spotify.com/v1/audio-analysis/5T8EDUDqKcs6OSOwEsfqG7",
                  "duration_ms": 209413,
                  "time_signature": 4
            },
            {
                  "danceability": 0.414,
                  "energy": 0.404,
                  "key": 0,
                  "loudness": -9.928,
                  "mode": 0,
                  "speechiness": 0.0499,
                  "acousticness": 0.271,
                  "instrumentalness": 0,
                  "liveness": 0.3,
                  "valence": 0.224,
                  "tempo": 71.105,
                  "type": "audio_features",
                  "id": "4u7EnebtmKWzUH433cf5Qv",
                  "uri": "spotify:track:4u7EnebtmKWzUH433cf5Qv",
                  "track_href": "https://api.spotify.com/v1/tracks/4u7EnebtmKWzUH433cf5Qv",
                  "analysis_url": "https://api.spotify.com/v1/audio-analysis/4u7EnebtmKWzUH433cf5Qv",
                  "duration_ms": 354320,
                  "time_signature": 4
            },
            {
                  "danceability": 0.933,
                  "energy": 0.528,
                  "key": 5,
                  "loudness": -6.472,
                  "mode": 0,
                  "speechiness": 0.161,
                  "acousticness": 0.112,
                  "instrumentalness": 0.312,
                  "liveness": 0.163,
                  "valence": 0.754,
                  "tempo": 109.967,
                  "type": "audio_features",
                  "id": "5vdp5UmvTsnMEMESIF2Ym7",
                  "uri": "spotify:track:5vdp5UmvTsnMEMESIF2Ym7",
                  "track_href": "https://api.spotify.com/v1/tracks/5vdp5UmvTsnMEMESIF2Ym7",
                  "analysis_url": "https://api.spotify.com/v1/audio-analysis/5vdp5UmvTsnMEMESIF2Ym7",
                  "duration_ms": 214653,
                  "time_signature": 4
            },
            {
                  "danceability": 0.654,
                  "energy": 0.828,
                  "key": 1,
                  "loudness": -5.377,
                  "mode": 0,
                  "speechiness": 0.0281,
                  "acousticness": 0.00146,
                  "instrumentalness": 0.000144,
                  "liveness": 0.122,
                  "valence": 0.79,
                  "tempo": 112.056,
                  "type": "audio_features",
                  "id": "2x8evxqUlF0eRabbW2JBJd",
                  "uri": "spotify:track:2x8evxqUlF0eRabbW2JBJd",
                  "track_href": "https://api.spotify.com/v1/tracks/2x8evxqUlF0eRabbW2JBJd",
                  "analysis_url": "https://api.spotify.com/v1/audio-analysis/2x8evxqUlF0eRabbW2JBJd",
                  "duration_ms": 183893,
                  "time_signature": 4
            },
            {
                  "danceability": 0.288,
                  "energy": 0.758,
                  "key": 6,
                  "loudness": -5.692,
                  "mode": 0,
                  "speechiness": 0.0371,
                  "acousticness": 0.00616,
                  "instrumentalness": 0,
                  "liveness": 0.303,
                  "valence": 0.619,
                  "tempo": 97.094,
                  "type": "audio_features",
                  "id": "2AT8iROs4FQueDv2c8q2KE",
                  "uri": "spotify:track:2AT8iROs4FQueDv2c8q2KE",
                  "track_href": "https://api.spotify.com/v1/tracks/2AT8iROs4FQueDv2c8q2KE",
                  "analysis_url": "https://api.spotify.com/v1/audio-analysis/2AT8iROs4FQueDv2c8q2KE",
                  "duration_ms": 201726,
                  "time_signature": 4
            },
            {
                  "danceability": 0.734,
                  "energy": 0.637,
                  "key": 4,
                  "loudness": -5.677,
                  "mode": 0,
                  "speechiness": 0.141,
                  "acousticness": 0.0462,
                  "instrumentalness": 2.29e-05,
                  "liveness": 0.0602,
                  "valence": 0.648,
                  "tempo": 169.977,
                  "type": "audio_features",
                  "id": "3CRDbSIZ4r5MsZ0YwxuEkn",
                  "uri": "spotify:track:3CRDbSIZ4r5MsZ0YwxuEkn",
                  "track_href": "https://api.spotify.com/v1/tracks/3CRDbSIZ4r5MsZ0YwxuEkn",
                  "analysis_url": "https://api.spotify.com/v1/audio-analysis/3CRDbSIZ4r5MsZ0YwxuEkn",
                  "duration_ms": 202333,
                  "time_signature": 4
            },
            {
                  "danceability": 0.548,
                  "energy": 0.532,
                  "key": 5,
                  "loudness": -7.596,
                  "mode": 1,
                  "speechiness": 0.0323,
                  "acousticness": 0.186,
                  "instrumentalness": 0.000263,
                  "liveness": 0.217,
                  "valence": 0.405,
                  "tempo": 85.03,
                  "type": "audio_features",
                  "id": "5FVd6KXrgO9B3JPmC8OPst",
                  "uri": "spotify:track:5FVd6KXrgO9B3JPmC8OPst",
                  "track_href": "https://api.spotify.com/v1/tracks/5FVd6KXrgO9B3JPmC8OPst",
                  "analysis_url": "https://api.spotify.com/v1/audio-analysis/5FVd6KXrgO9B3JPmC8OPst",
                  "duration_ms": 272394,
                  "time_signature": 4
            },
            {
                  "danceability": 0.524,
                  "energy": 0.742,
                  "key": 1,
                  "loudness": -6.754,
                  "mode": 1,
                  "speechiness": 0.106,
                  "acousticness": 0.0462,
                  "instrumentalness": 5.17e-05,
                  "liveness": 0.146,
                  "valence": 0.478,
                  "tempo": 184.014,
                  "type": "audio_features",
                  "id": "3ZV6Ry07586w52Wy1cLbLL",
                  "uri": "spotify:track:3ZV6Ry07586w52Wy1cLbLL",
                  "track_href": "https://api.spotify.com/v1/tracks/3ZV6Ry07586w52Wy1cLbLL",
                  "analysis_url": "https://api.spotify.com/v1/audio-analysis/3ZV6Ry07586w52Wy1cLbLL",
                  "duration_ms": 208520,
                  "time_signature": 4
            },
            {
                  "danceability": 0.729,
                  "energy": 0.844,
                  "key": 5,
                  "loudness": -8.824,
                  "mode": 1,
                  "speechiness": 0.0344,
                  "acousticness": 0.149,
                  "instrumentalness": 2.87e-06,
                  "liveness": 0.0604,
                  "valence": 0.777,
                  "tempo": 131.459,
                  "type": "audio_features",
                  "id": "7HW5WIw7ZgZORCzUxv5gW5",
                  "uri": "spotify:track:7HW5WIw7ZgZORCzUxv5gW5",
                  "track_href": "https://api.spotify.com/v1/tracks/7HW5WIw7ZgZORCzUxv5gW5",
                  "analysis_url": "https://api.spotify.com/v1/audio-analysis/7HW5WIw7ZgZORCzUxv5gW5",
                  "duration_ms": 275440,
                  "time_signature": 4
            },
            {
                  "danceability": 0.554,
                  "energy": 0.315,
                  "key": 3,
                  "loudness": -11.028,
                  "mode": 1,
                  "speechiness": 0.0298,
                  "acousticness": 0.828,
                  "instrumentalness": 5.53e-06,
                  "liveness": 0.101,
                  "valence": 0.325,
                  "tempo": 128.157,
                  "type": "audio_features",
                  "id": "38zsOOcu31XbbYj9BIPUF1",
                  "uri": "spotify:track:38zsOOcu31XbbYj9BIPUF1",
                  "track_href": "https://api.spotify.com/v1/tracks/38zsOOcu31XbbYj9BIPUF1",
                  "analysis_url": "https://api.spotify.com/v1/audio-analysis/38zsOOcu31XbbYj9BIPUF1",
                  "duration_ms": 241787,
                  "time_signature": 4
            },
            {
                  "danceability": 0.524,
                  "energy": 0.742,
                  "key": 1,
                  "loudness": -6.754,
                  "mode": 1,
                  "speechiness": 0.106,
                  "acousticness": 0.0462,
                  "instrumentalness": 5.17e-05,
                  "liveness": 0.146,
                  "valence": 0.478,
                  "tempo": 184.014,
                  "type": "audio_features",
                  "id": "3ZV6Ry07586w52Wy1cLbLL",
                  "uri": "spotify:track:3ZV6Ry07586w52Wy1cLbLL",
                  "track_href": "https://api.spotify.com/v1/tracks/3ZV6Ry07586w52Wy1cLbLL",
                  "analysis_url": "https://api.spotify.com/v1/audio-analysis/3ZV6Ry07586w52Wy1cLbLL",
                  "duration_ms": 208520,
                  "time_signature": 4
            },
            {
                  "danceability": 0.698,
                  "energy": 0.649,
                  "key": 8,
                  "loudness": -6.764,
                  "mode": 1,
                  "speechiness": 0.415,
                  "acousticness": 0.15,
                  "instrumentalness": 0,
                  "liveness": 0.0903,
                  "valence": 0.568,
                  "tempo": 180.466,
                  "type": "audio_features",
                  "id": "4cxvludVmQxryrnx1m9FqL",
                  "uri": "spotify:track:4cxvludVmQxryrnx1m9FqL",
                  "track_href": "https://api.spotify.com/v1/tracks/4cxvludVmQxryrnx1m9FqL",
                  "analysis_url": "https://api.spotify.com/v1/audio-analysis/4cxvludVmQxryrnx1m9FqL",
                  "duration_ms": 333154,
                  "time_signature": 4
            },
            {
                  "danceability": 0.646,
                  "energy": 0.439,
                  "key": 7,
                  "loudness": -10.837,
                  "mode": 1,
                  "speechiness": 0.818,
                  "acousticness": 0.272,
                  "instrumentalness": 0,
                  "liveness": 0.0945,
                  "valence": 0.528,
                  "tempo": 160.387,
                  "type": "audio_features",
                  "id": "6dr7ekfhlbquvsVY8D7gyk",
                  "uri": "spotify:track:6dr7ekfhlbquvsVY8D7gyk",
                  "track_href": "https://api.spotify.com/v1/tracks/6dr7ekfhlbquvsVY8D7gyk",
                  "analysis_url": "https://api.spotify.com/v1/audio-analysis/6dr7ekfhlbquvsVY8D7gyk",
                  "duration_ms": 156631,
                  "time_signature": 4
            },
            {
                  "danceability": 0.609,
                  "energy": 0.435,
                  "key": 11,
                  "loudness": -7.861,
                  "mode": 0,
                  "speechiness": 0.285,
                  "acousticness": 0.522,
                  "instrumentalness": 0,
                  "liveness": 0.118,
                  "valence": 0.552,
                  "tempo": 131.995,
                  "type": "audio_features",
                  "id": "4TTV7EcfroSLWzXRY6gLv6",
                  "uri": "spotify:track:4TTV7EcfroSLWzXRY6gLv6",
                  "track_href": "https://api.spotify.com/v1/tracks/4TTV7EcfroSLWzXRY6gLv6",
                  "analysis_url": "https://api.spotify.com/v1/audio-analysis/4TTV7EcfroSLWzXRY6gLv6",
                  "duration_ms": 236738,
                  "time_signature": 4
            },
            {
                  "danceability": 0.609,
                  "energy": 0.435,
                  "key": 11,
                  "loudness": -7.861,
                  "mode": 0,
                  "speechiness": 0.285,
                  "acousticness": 0.522,
                  "instrumentalness": 0,
                  "liveness": 0.118,
                  "valence": 0.552,
                  "tempo": 131.995,
                  "type": "audio_features",
                  "id": "4TTV7EcfroSLWzXRY6gLv6",
                  "uri": "spotify:track:4TTV7EcfroSLWzXRY6gLv6",
                  "track_href": "https://api.spotify.com/v1/tracks/4TTV7EcfroSLWzXRY6gLv6",
                  "analysis_url": "https://api.spotify.com/v1/audio-analysis/4TTV7EcfroSLWzXRY6gLv6",
                  "duration_ms": 236738,
                  "time_signature": 4
            },
            {
                  "danceability": 0.646,
                  "energy": 0.439,
                  "key": 7,
                  "loudness": -10.837,
                  "mode": 1,
                  "speechiness": 0.818,
                  "acousticness": 0.272,
                  "instrumentalness": 0,
                  "liveness": 0.0945,
                  "valence": 0.528,
                  "tempo": 160.387,
                  "type": "audio_features",
                  "id": "6dr7ekfhlbquvsVY8D7gyk",
                  "uri": "spotify:track:6dr7ekfhlbquvsVY8D7gyk",
                  "track_href": "https://api.spotify.com/v1/tracks/6dr7ekfhlbquvsVY8D7gyk",
                  "analysis_url": "https://api.spotify.com/v1/audio-analysis/6dr7ekfhlbquvsVY8D7gyk",
                  "duration_ms": 156631,
                  "time_signature": 4
            },
            {
                  "danceability": 0.609,
                  "energy": 0.435,
                  "key": 11,
                  "loudness": -7.861,
                  "mode": 0,
                  "speechiness": 0.285,
                  "acousticness": 0.522,
                  "instrumentalness": 0,
                  "liveness": 0.118,
                  "valence": 0.552,
                  "tempo": 131.995,
                  "type": "audio_features",
                  "id": "4TTV7EcfroSLWzXRY6gLv6",
                  "uri": "spotify:track:4TTV7EcfroSLWzXRY6gLv6",
                  "track_href": "https://api.spotify.com/v1/tracks/4TTV7EcfroSLWzXRY6gLv6",
                  "analysis_url": "https://api.spotify.com/v1/audio-analysis/4TTV7EcfroSLWzXRY6gLv6",
                  "duration_ms": 236738,
                  "time_signature": 4
            }
      ]
}